data_storage/__init__.py
data_storage/standard_workflows/__init__.py
nylon/__init__.py
nylon/fetcher.py
nylon/query.py
nylon/analysis/__init__.py
nylon/analysis/analysis.py
nylon/data/__init__.py
nylon/data/reader.py
nylon/modeling/__init__.py
nylon/modeling/modeling.py
nylon/preprocessing/__init__.py
nylon/preprocessing/preprocessing.py
nylon/preprocessing/preprocessing_inference.py
nylon/preprocessing/preprocessing_methods.py
nylon/supplementaries/__init__.py
nylon/supplementaries/handlers.py
nylon/supplementaries/main.py
nylon_ai-0.0.7.dist-info/LICENSE
nylon_ai-0.0.7.dist-info/METADATA
nylon_ai-0.0.7.dist-info/WHEEL
nylon_ai-0.0.7.dist-info/top_level.txt
nylon_ai-0.0.7.dist-info/RECORD
